ckuehl_pre_commit_types-0.7.6.dev1.dist-info/entry_points.txt
ckuehl_pre_commit_types-0.7.6.dev1.dist-info/top_level.txt
ckuehl_pre_commit_types-0.7.6.dev1.dist-info/METADATA
ckuehl_pre_commit_types-0.7.6.dev1.dist-info/metadata.json
ckuehl_pre_commit_types-0.7.6.dev1.dist-info/WHEEL
ckuehl_pre_commit_types-0.7.6.dev1.dist-info/DESCRIPTION.rst
ckuehl_pre_commit_types-0.7.6.dev1.dist-info/RECORD
pre_commit/runner.py
pre_commit/logging_handler.py
pre_commit/main.py
pre_commit/util.py
pre_commit/make_archives.py
pre_commit/jsonschema_extensions.py
pre_commit/store.py
pre_commit/error_handler.py
pre_commit/color.py
pre_commit/git.py
pre_commit/ordereddict.py
pre_commit/staged_files_only.py
pre_commit/__main__.py
pre_commit/constants.py
pre_commit/__init__.py
pre_commit/prefixed_command_runner.py
pre_commit/output.py
pre_commit/repository.py
pre_commit/five.py
pre_commit/errors.py
pre_commit/manifest.py
pre_commit/languages/system.py
pre_commit/languages/python.py
pre_commit/languages/pcre.py
pre_commit/languages/node.py
pre_commit/languages/ruby.py
pre_commit/languages/all.py
pre_commit/languages/__init__.py
pre_commit/languages/script.py
pre_commit/languages/helpers.py
pre_commit/clientlib/validate_config.py
pre_commit/clientlib/__init__.py
pre_commit/clientlib/validate_base.py
pre_commit/clientlib/validate_manifest.py
pre_commit/resources/rbenv.tar.gz
pre_commit/resources/ruby-download.tar.gz
pre_commit/resources/pre-push-tmpl
pre_commit/resources/hook-tmpl
pre_commit/resources/ruby-build.tar.gz
pre_commit/file_classifier/interpreters.py
pre_commit/file_classifier/__init__.py
pre_commit/file_classifier/classifier.py
pre_commit/file_classifier/extensions.py
pre_commit/commands/identify.py
pre_commit/commands/clean.py
pre_commit/commands/autoupdate.py
pre_commit/commands/__init__.py
pre_commit/commands/install_uninstall.py
pre_commit/commands/run.py
