Metadata-Version: 2.0
Name: ckuehl-pre-commit-types
Version: 0.7.6.dev1
Summary: A framework for managing and maintaining multi-language pre-commit hooks.
Home-page: https://github.com/pre-commit/pre-commit
Author: Chris Kuehl (testing fork), Anthony Sottile
Author-email: ckuehl@yelp.com
License: UNKNOWN
Platform: linux
Classifier: License :: OSI Approved :: MIT License
Classifier: Programming Language :: Python :: 2
Classifier: Programming Language :: Python :: 2.6
Classifier: Programming Language :: Python :: 2.7
Classifier: Programming Language :: Python :: 3
Classifier: Programming Language :: Python :: 3.3
Classifier: Programming Language :: Python :: 3.4
Classifier: Programming Language :: Python :: 3.5
Classifier: Programming Language :: Python :: Implementation :: CPython
Classifier: Programming Language :: Python :: Implementation :: PyPy
Requires-Dist: argparse
Requires-Dist: aspy.yaml
Requires-Dist: cached-property
Requires-Dist: jsonschema
Requires-Dist: nodeenv (>=0.11.1)
Requires-Dist: ordereddict
Requires-Dist: pyyaml
Requires-Dist: virtualenv
